{
    "created_at": "Fri Jun 07 12:30:41 +0000 2019",
    "hashtags": [],
    "id": 1136973754842656774,
    "id_str": "1136973754842656774",
    "lang": "en",
    "retweet_count": 9,
    "retweeted_status": {
        "created_at": "Fri Jun 07 03:46:39 +0000 2019",
        "favorite_count": 31,
        "hashtags": [],
        "id": 1136841877552914434,
        "id_str": "1136841877552914434",
        "lang": "en",
        "retweet_count": 9,
        "source": "<a href=\"http://twitter.com/download/iphone\" rel=\"nofollow\">Twitter for iPhone</a>",
        "text": "We can have clean air! Cars and trucks are still the largest source of emissions. Here are our recommendations for\u2026 https://t.co/dcK543UjcZ",
        "truncated": true,
        "urls": [
            {
                "expanded_url": "https://twitter.com/i/web/status/1136841877552914434",
                "url": "https://t.co/dcK543UjcZ"
            }
        ],
        "user": {
            "created_at": "Thu Aug 18 21:49:07 +0000 2011",
            "default_profile": true,
            "description": "Happy husband and father. Former east coaster and midwesterner, current westerner. Executive Director, Wasatch Front Regional Council, Utah @wasatchcouncil",
            "favourites_count": 1840,
            "followers_count": 480,
            "friends_count": 588,
            "id": 357771855,
            "id_str": "357771855",
            "listed_count": 6,
            "name": "Andrew Gruber",
            "profile_background_color": "C0DEED",
            "profile_background_image_url": "http://abs.twimg.com/images/themes/theme1/bg.png",
            "profile_background_image_url_https": "https://abs.twimg.com/images/themes/theme1/bg.png",
            "profile_image_url": "http://pbs.twimg.com/profile_images/768594672025337856/UATlN-45_normal.jpg",
            "profile_image_url_https": "https://pbs.twimg.com/profile_images/768594672025337856/UATlN-45_normal.jpg",
            "profile_link_color": "1DA1F2",
            "profile_sidebar_border_color": "C0DEED",
            "profile_sidebar_fill_color": "DDEEF6",
            "profile_text_color": "333333",
            "profile_use_background_image": true,
            "screen_name": "GruberAndrew",
            "statuses_count": 349
        },
        "user_mentions": []
    },
    "source": "<a href=\"http://twitter.com/download/iphone\" rel=\"nofollow\">Twitter for iPhone</a>",
    "text": "RT @GruberAndrew: We can have clean air! Cars and trucks are still the largest source of emissions. Here are our recommendations for 5 ways\u2026",
    "urls": [],
    "user": {
        "created_at": "Fri Nov 17 20:06:16 +0000 2017",
        "description": "Official account for Congressman John Curtis, self-proclaimed millennial. Proudly serving the people of Utah's 3rd district.",
        "favourites_count": 1059,
        "followers_count": 3244,
        "friends_count": 197,
        "geo_enabled": true,
        "id": 931614483050414080,
        "id_str": "931614483050414080",
        "listed_count": 164,
        "location": "Utah and DC",
        "name": "Rep. John Curtis",
        "profile_background_color": "000000",
        "profile_background_image_url": "http://abs.twimg.com/images/themes/theme1/bg.png",
        "profile_background_image_url_https": "https://abs.twimg.com/images/themes/theme1/bg.png",
        "profile_banner_url": "https://pbs.twimg.com/profile_banners/931614483050414080/1552422198",
        "profile_image_url": "http://pbs.twimg.com/profile_images/1143191800548663299/9Ffm2sDG_normal.png",
        "profile_image_url_https": "https://pbs.twimg.com/profile_images/1143191800548663299/9Ffm2sDG_normal.png",
        "profile_link_color": "6C7614",
        "profile_sidebar_border_color": "000000",
        "profile_sidebar_fill_color": "000000",
        "profile_text_color": "000000",
        "screen_name": "RepJohnCurtis",
        "statuses_count": 1739,
        "url": "https://t.co/EXDQ281Hrl",
        "verified": true
    },
    "user_mentions": [
        {
            "id": 357771855,
            "id_str": "357771855",
            "name": "Andrew Gruber",
            "screen_name": "GruberAndrew"
        }
    ]
}