{
    "created_at": "Mon Aug 12 01:29:31 +0000 2019",
    "hashtags": [],
    "id": 1160724965173473281,
    "id_str": "1160724965173473281",
    "lang": "en",
    "retweet_count": 1305,
    "retweeted_status": {
        "created_at": "Sun Aug 11 23:06:04 +0000 2019",
        "favorite_count": 6267,
        "hashtags": [],
        "id": 1160688865650364416,
        "id_str": "1160688865650364416",
        "lang": "en",
        "retweet_count": 1305,
        "source": "<a href=\"https://about.twitter.com/products/tweetdeck\" rel=\"nofollow\">TweetDeck</a>",
        "text": "In the Senate, @SenFeinstein and I led the successful effort to ban assault weapons and high-capacity magazines. It\u2026 https://t.co/7GmtX0VE3K",
        "truncated": true,
        "urls": [
            {
                "expanded_url": "https://twitter.com/i/web/status/1160688865650364416",
                "url": "https://t.co/7GmtX0VE3K"
            }
        ],
        "user": {
            "created_at": "Sun Mar 11 17:51:24 +0000 2007",
            "description": "Senator, Vice President, 2020 candidate for President of the United States, husband to @DrBiden, proud father & grandfather. Loves ice cream, aviators & @Amtrak",
            "favourites_count": 16,
            "followers_count": 3679666,
            "friends_count": 22,
            "id": 939091,
            "id_str": "939091",
            "listed_count": 14109,
            "location": "Wilmington, DE",
            "name": "Joe Biden",
            "profile_background_color": "565959",
            "profile_background_image_url": "http://abs.twimg.com/images/themes/theme1/bg.png",
            "profile_background_image_url_https": "https://abs.twimg.com/images/themes/theme1/bg.png",
            "profile_background_tile": true,
            "profile_banner_url": "https://pbs.twimg.com/profile_banners/939091/1558224273",
            "profile_image_url": "http://pbs.twimg.com/profile_images/1153646262526369793/f4GqlaQL_normal.png",
            "profile_image_url_https": "https://pbs.twimg.com/profile_images/1153646262526369793/f4GqlaQL_normal.png",
            "profile_link_color": "233F94",
            "profile_sidebar_border_color": "FFFFFF",
            "profile_sidebar_fill_color": "EBEBFF",
            "profile_text_color": "323232",
            "profile_use_background_image": true,
            "screen_name": "JoeBiden",
            "statuses_count": 2347,
            "url": "https://t.co/UClrPuJpyZ",
            "verified": true
        },
        "user_mentions": [
            {
                "id": 476256944,
                "id_str": "476256944",
                "name": "Sen Dianne Feinstein",
                "screen_name": "SenFeinstein"
            }
        ]
    },
    "source": "<a href=\"http://twitter.com/download/iphone\" rel=\"nofollow\">Twitter for iPhone</a>",
    "text": "RT @JoeBiden: In the Senate, @SenFeinstein and I led the successful effort to ban assault weapons and high-capacity magazines. It worked. I\u2026",
    "urls": [],
    "user": {
        "created_at": "Mon May 31 01:22:43 +0000 2010",
        "default_profile": true,
        "description": "U.S. Senator from Connecticut.",
        "favourites_count": 1211,
        "followers_count": 790138,
        "friends_count": 200,
        "geo_enabled": true,
        "id": 150078976,
        "id_str": "150078976",
        "listed_count": 5248,
        "name": "Chris Murphy",
        "profile_background_color": "C0DEED",
        "profile_background_image_url": "http://abs.twimg.com/images/themes/theme1/bg.png",
        "profile_background_image_url_https": "https://abs.twimg.com/images/themes/theme1/bg.png",
        "profile_banner_url": "https://pbs.twimg.com/profile_banners/150078976/1542228542",
        "profile_image_url": "http://pbs.twimg.com/profile_images/871076844904361985/7NorOQHB_normal.jpg",
        "profile_image_url_https": "https://pbs.twimg.com/profile_images/871076844904361985/7NorOQHB_normal.jpg",
        "profile_link_color": "1DA1F2",
        "profile_sidebar_border_color": "C0DEED",
        "profile_sidebar_fill_color": "DDEEF6",
        "profile_text_color": "333333",
        "profile_use_background_image": true,
        "screen_name": "ChrisMurphyCT",
        "statuses_count": 19322,
        "verified": true
    },
    "user_mentions": [
        {
            "id": 939091,
            "id_str": "939091",
            "name": "Joe Biden",
            "screen_name": "JoeBiden"
        },
        {
            "id": 476256944,
            "id_str": "476256944",
            "name": "Sen Dianne Feinstein",
            "screen_name": "SenFeinstein"
        }
    ]
}