{
    "created_at": "Thu May 09 22:46:02 +0000 2019",
    "favorite_count": 12,
    "hashtags": [],
    "id": 1126619363526750210,
    "id_str": "1126619363526750210",
    "lang": "en",
    "retweet_count": 2,
    "source": "<a href=\"http://twitter.com\" rel=\"nofollow\">Twitter Web Client</a>",
    "text": "Today I voted against a bill that has nothing to do with pre-existing conditions. The inappropriately named Protect\u2026 https://t.co/8eEf3UYQ0Q",
    "truncated": true,
    "urls": [
        {
            "expanded_url": "https://twitter.com/i/web/status/1126619363526750210",
            "url": "https://t.co/8eEf3UYQ0Q"
        }
    ],
    "user": {
        "created_at": "Fri Jul 11 18:33:24 +0000 2008",
        "description": "Representing #OH5. Deputy Whip. Member of @HouseCommerce Committee. Republican Leader of the Communications and Technology Subcommittee.",
        "favourites_count": 531,
        "followers_count": 37776,
        "friends_count": 2943,
        "geo_enabled": true,
        "id": 15394954,
        "id_str": "15394954",
        "listed_count": 1348,
        "name": "U.S. Rep. Bob Latta",
        "profile_background_color": "4F4F4F",
        "profile_background_image_url": "http://abs.twimg.com/images/themes/theme1/bg.png",
        "profile_background_image_url_https": "https://abs.twimg.com/images/themes/theme1/bg.png",
        "profile_banner_url": "https://pbs.twimg.com/profile_banners/15394954/1436980975",
        "profile_image_url": "http://pbs.twimg.com/profile_images/621369511636135937/Zk5PgsWw_normal.jpg",
        "profile_image_url_https": "https://pbs.twimg.com/profile_images/621369511636135937/Zk5PgsWw_normal.jpg",
        "profile_link_color": "3B94D9",
        "profile_sidebar_border_color": "550000",
        "profile_sidebar_fill_color": "B2CEED",
        "profile_text_color": "333333",
        "profile_use_background_image": true,
        "screen_name": "boblatta",
        "statuses_count": 7125,
        "url": "http://t.co/dSKBcpo6FL",
        "verified": true
    },
    "user_mentions": []
}