{
    "created_at": "Thu Mar 28 13:32:35 +0000 2019",
    "favorite_count": 11,
    "hashtags": [],
    "id": 1111259794407591936,
    "id_str": "1111259794407591936",
    "lang": "en",
    "media": [
        {
            "display_url": "pic.twitter.com/mPHxN77BND",
            "expanded_url": "https://twitter.com/RepLarryBucshon/status/1111259794407591936/video/1",
            "id": 1111259748945543168,
            "media_url": "http://pbs.twimg.com/ext_tw_video_thumb/1111259748945543168/pu/img/FvRDSKKQ_p6kDQ2k.jpg",
            "media_url_https": "https://pbs.twimg.com/ext_tw_video_thumb/1111259748945543168/pu/img/FvRDSKKQ_p6kDQ2k.jpg",
            "sizes": {
                "thumb": {
                    "w": 150,
                    "h": 150,
                    "resize": "crop"
                },
                "medium": {
                    "w": 1200,
                    "h": 675,
                    "resize": "fit"
                },
                "small": {
                    "w": 680,
                    "h": 383,
                    "resize": "fit"
                },
                "large": {
                    "w": 1280,
                    "h": 720,
                    "resize": "fit"
                }
            },
            "type": "video",
            "url": "https://t.co/mPHxN77BND",
            "video_info": {
                "aspect_ratio": [
                    16,
                    9
                ],
                "duration_millis": 66867,
                "variants": [
                    {
                        "content_type": "application/x-mpegURL",
                        "url": "https://video.twimg.com/ext_tw_video/1111259748945543168/pu/pl/eEY5aXmsqvUFr1To.m3u8?tag=8"
                    },
                    {
                        "bitrate": 2176000,
                        "content_type": "video/mp4",
                        "url": "https://video.twimg.com/ext_tw_video/1111259748945543168/pu/vid/1280x720/hsh69rnMsiV7RUx-.mp4?tag=8"
                    },
                    {
                        "bitrate": 832000,
                        "content_type": "video/mp4",
                        "url": "https://video.twimg.com/ext_tw_video/1111259748945543168/pu/vid/640x360/5Lp_CWInDP3ExaoF.mp4?tag=8"
                    },
                    {
                        "bitrate": 256000,
                        "content_type": "video/mp4",
                        "url": "https://video.twimg.com/ext_tw_video/1111259748945543168/pu/vid/320x180/0aUS0oXYnv8_Kt8m.mp4?tag=8"
                    }
                ]
            }
        }
    ],
    "retweet_count": 1,
    "source": "<a href=\"https://mobile.twitter.com\" rel=\"nofollow\">Twitter Web App</a>",
    "text": "Congratulations to the @VincennesU Men's basketball team on winning the NJCAA national championship! https://t.co/mPHxN77BND",
    "urls": [],
    "user": {
        "created_at": "Thu Jan 06 16:45:56 +0000 2011",
        "description": "Congressman representing Hoosiers from #IN08. Doctor. Member of @HouseCommerce. https://t.co/4eq38gWLlg",
        "favourites_count": 684,
        "followers_count": 21251,
        "friends_count": 1969,
        "geo_enabled": true,
        "id": 234812598,
        "id_str": "234812598",
        "listed_count": 935,
        "location": "Indiana's 8th District",
        "name": "Larry Bucshon, MD",
        "profile_background_color": "C0DEED",
        "profile_background_image_url": "http://abs.twimg.com/images/themes/theme1/bg.png",
        "profile_background_image_url_https": "https://abs.twimg.com/images/themes/theme1/bg.png",
        "profile_banner_url": "https://pbs.twimg.com/profile_banners/234812598/1528127787",
        "profile_image_url": "http://pbs.twimg.com/profile_images/3781635770/569620c6e7f294f1f1fed50b41b3ab77_normal.jpeg",
        "profile_image_url_https": "https://pbs.twimg.com/profile_images/3781635770/569620c6e7f294f1f1fed50b41b3ab77_normal.jpeg",
        "profile_link_color": "0084B4",
        "profile_sidebar_border_color": "FFFFFF",
        "profile_sidebar_fill_color": "DDEEF6",
        "profile_text_color": "333333",
        "profile_use_background_image": true,
        "screen_name": "RepLarryBucshon",
        "statuses_count": 5541,
        "url": "https://t.co/wPeLTvPae3",
        "verified": true
    },
    "user_mentions": [
        {
            "id": 79018651,
            "id_str": "79018651",
            "name": "Vincennes University",
            "screen_name": "VincennesU"
        }
    ]
}