{
    "created_at": "Mon Aug 06 17:22:45 +0000 2018",
    "hashtags": [
        {
            "text": "DonnellFire"
        }
    ],
    "id": 1026518955282890755,
    "id_str": "1026518955282890755",
    "lang": "en",
    "retweet_count": 20,
    "retweeted_status": {
        "created_at": "Mon Aug 06 14:12:56 +0000 2018",
        "favorite_count": 19,
        "hashtags": [
            {
                "text": "DonnellFire"
            }
        ],
        "id": 1026471186723524608,
        "id_str": "1026471186723524608",
        "lang": "en",
        "media": [
            {
                "display_url": "pic.twitter.com/FRs5NSR0gr",
                "expanded_url": "https://twitter.com/TuolumneSheriff/status/1026471186723524608/photo/1",
                "id": 1026471181099003906,
                "media_url": "http://pbs.twimg.com/media/Dj7CGcmU8AIqXCO.jpg",
                "media_url_https": "https://pbs.twimg.com/media/Dj7CGcmU8AIqXCO.jpg",
                "sizes": {
                    "thumb": {
                        "w": 150,
                        "h": 150,
                        "resize": "crop"
                    },
                    "medium": {
                        "w": 640,
                        "h": 480,
                        "resize": "fit"
                    },
                    "small": {
                        "w": 640,
                        "h": 480,
                        "resize": "fit"
                    },
                    "large": {
                        "w": 640,
                        "h": 480,
                        "resize": "fit"
                    }
                },
                "type": "photo",
                "url": "https://t.co/FRs5NSR0gr"
            }
        ],
        "retweet_count": 20,
        "source": "<a href=\"http://twitter.com/download/iphone\" rel=\"nofollow\">Twitter for iPhone</a>",
        "text": "#DonnellFire is estimated at 6000 acres with 2 % containment. All Mandatory Evacuation Orders are still in effect. https://t.co/FRs5NSR0gr",
        "urls": [],
        "user": {
            "created_at": "Mon Aug 24 21:05:12 +0000 2015",
            "default_profile": true,
            "favourites_count": 642,
            "followers_count": 1738,
            "friends_count": 112,
            "id": 3330122538,
            "id_str": "3330122538",
            "listed_count": 59,
            "location": "Sonora, Ca",
            "name": "Tuolumne Co. Sheriff",
            "profile_background_color": "C0DEED",
            "profile_background_image_url": "http://abs.twimg.com/images/themes/theme1/bg.png",
            "profile_background_image_url_https": "https://abs.twimg.com/images/themes/theme1/bg.png",
            "profile_banner_url": "https://pbs.twimg.com/profile_banners/3330122538/1553823388",
            "profile_image_url": "http://pbs.twimg.com/profile_images/1080601857926389765/pLb1Qcgh_normal.jpg",
            "profile_image_url_https": "https://pbs.twimg.com/profile_images/1080601857926389765/pLb1Qcgh_normal.jpg",
            "profile_link_color": "1DA1F2",
            "profile_sidebar_border_color": "C0DEED",
            "profile_sidebar_fill_color": "DDEEF6",
            "profile_text_color": "333333",
            "profile_use_background_image": true,
            "screen_name": "TuolumneSheriff",
            "statuses_count": 958,
            "url": "https://t.co/IHstRo3xV5"
        },
        "user_mentions": []
    },
    "source": "<a href=\"https://mobile.twitter.com\" rel=\"nofollow\">Twitter Web App</a>",
    "text": "RT @TuolumneSheriff: #DonnellFire is estimated at 6000 acres with 2 % containment. All Mandatory Evacuation Orders are still in effect. htt\u2026",
    "urls": [],
    "user": {
        "created_at": "Wed Jun 24 00:21:07 +0000 2009",
        "description": "United States Representative, 4th District of California",
        "favourites_count": 1,
        "followers_count": 14559,
        "id": 50152441,
        "id_str": "50152441",
        "listed_count": 1204,
        "location": "Washington, DC",
        "name": "Tom McClintock",
        "profile_background_color": "093552",
        "profile_background_image_url": "http://abs.twimg.com/images/themes/theme1/bg.png",
        "profile_background_image_url_https": "https://abs.twimg.com/images/themes/theme1/bg.png",
        "profile_image_url": "http://pbs.twimg.com/profile_images/416902006/McClintockphoto1_normal.jpg",
        "profile_image_url_https": "https://pbs.twimg.com/profile_images/416902006/McClintockphoto1_normal.jpg",
        "profile_link_color": "3078B8",
        "profile_sidebar_border_color": "C0DEED",
        "profile_sidebar_fill_color": "DDEEF6",
        "profile_text_color": "333333",
        "profile_use_background_image": true,
        "screen_name": "RepMcClintock",
        "statuses_count": 496,
        "url": "http://t.co/M52pLVZcTJ",
        "verified": true
    },
    "user_mentions": [
        {
            "id": 3330122538,
            "id_str": "3330122538",
            "name": "Tuolumne Co. Sheriff",
            "screen_name": "TuolumneSheriff"
        }
    ]
}