{
    "created_at": "Sat May 04 02:00:58 +0000 2019",
    "favorite_count": 4118,
    "hashtags": [],
    "id": 1124494094452051968,
    "id_str": "1124494094452051968",
    "lang": "en",
    "retweet_count": 2318,
    "source": "<a href=\"http://twitter.com/download/iphone\" rel=\"nofollow\">Twitter for iPhone</a>",
    "text": ".@Jack, blocking @RealJamesWoods from Twitter, but not @LouisFarrakhan? Even @HamasInfoEn (Hamas) and @ikhwanweb (M\u2026 https://t.co/xIOxSYKCoJ",
    "truncated": true,
    "urls": [
        {
            "expanded_url": "https://twitter.com/i/web/status/1124494094452051968",
            "url": "https://t.co/xIOxSYKCoJ"
        }
    ],
    "user": {
        "created_at": "Wed Aug 20 19:25:47 +0000 2014",
        "default_profile": true,
        "description": "Proudly representing New York's First Congressional District.",
        "favourites_count": 23,
        "followers_count": 86751,
        "friends_count": 1859,
        "id": 2750127259,
        "id_str": "2750127259",
        "listed_count": 962,
        "name": "Lee Zeldin",
        "profile_background_color": "C0DEED",
        "profile_background_image_url": "http://abs.twimg.com/images/themes/theme1/bg.png",
        "profile_background_image_url_https": "https://abs.twimg.com/images/themes/theme1/bg.png",
        "profile_banner_url": "https://pbs.twimg.com/profile_banners/2750127259/1522445343",
        "profile_image_url": "http://pbs.twimg.com/profile_images/866759502867161088/ZGcdQunZ_normal.jpg",
        "profile_image_url_https": "https://pbs.twimg.com/profile_images/866759502867161088/ZGcdQunZ_normal.jpg",
        "profile_link_color": "1DA1F2",
        "profile_sidebar_border_color": "C0DEED",
        "profile_sidebar_fill_color": "DDEEF6",
        "profile_text_color": "333333",
        "profile_use_background_image": true,
        "screen_name": "RepLeeZeldin",
        "statuses_count": 2307,
        "url": "https://t.co/Kj9kXazM0U",
        "verified": true
    },
    "user_mentions": [
        {
            "id": 12,
            "id_str": "12",
            "name": "jack \ud83c\udf0d\ud83c\udf0f\ud83c\udf0e",
            "screen_name": "jack"
        },
        {
            "id": 78523300,
            "id_str": "78523300",
            "name": "James Woods",
            "screen_name": "RealJamesWoods"
        },
        {
            "id": 273469546,
            "id_str": "273469546",
            "name": "MINISTER FARRAKHAN",
            "screen_name": "LouisFarrakhan"
        },
        {
            "id": 3078990137,
            "id_str": "3078990137",
            "name": "Hamas Movement",
            "screen_name": "HamasInfoEn"
        },
        {
            "id": 41795342,
            "id_str": "41795342",
            "name": "Ikhwanweb",
            "screen_name": "Ikhwanweb"
        }
    ]
}