{
    "created_at": "Tue Jun 25 20:35:33 +0000 2019",
    "hashtags": [
        {
            "text": "Idaho"
        },
        {
            "text": "NIH"
        },
        {
            "text": "NIHinYourState"
        }
    ],
    "id": 1143618754863087617,
    "id_str": "1143618754863087617",
    "lang": "en",
    "retweet_count": 7,
    "retweeted_status": {
        "created_at": "Tue Jun 25 14:00:01 +0000 2019",
        "favorite_count": 11,
        "hashtags": [
            {
                "text": "Idaho"
            },
            {
                "text": "NIH"
            },
            {
                "text": "NIHinYourState"
            }
        ],
        "id": 1143519215560736768,
        "id_str": "1143519215560736768",
        "lang": "en",
        "media": [
            {
                "display_url": "pic.twitter.com/RQqIgFm6iZ",
                "expanded_url": "https://twitter.com/NIH/status/1143519215560736768/photo/1",
                "id": 1003637503717511168,
                "media_url": "http://pbs.twimg.com/media/De2i_fxXkAAWuYk.jpg",
                "media_url_https": "https://pbs.twimg.com/media/De2i_fxXkAAWuYk.jpg",
                "sizes": {
                    "thumb": {
                        "w": 150,
                        "h": 150,
                        "resize": "crop"
                    },
                    "medium": {
                        "w": 1200,
                        "h": 795,
                        "resize": "fit"
                    },
                    "small": {
                        "w": 680,
                        "h": 451,
                        "resize": "fit"
                    },
                    "large": {
                        "w": 1280,
                        "h": 848,
                        "resize": "fit"
                    }
                },
                "type": "photo",
                "url": "https://t.co/RQqIgFm6iZ"
            }
        ],
        "retweet_count": 7,
        "source": "<a href=\"https://ads.twitter.com\" rel=\"nofollow\">Twitter Ads</a>",
        "text": "#Idaho received $14.9 million in #NIH-funded research support in FY2018: https://t.co/8nk4PbrH0L #NIHinYourState https://t.co/RQqIgFm6iZ",
        "urls": [
            {
                "expanded_url": "https://bit.ly/2Jz5nFJ",
                "url": "https://t.co/8nk4PbrH0L"
            }
        ],
        "user": {
            "created_at": "Mon Jun 16 13:57:45 +0000 2008",
            "description": "Official Twitter account of the National Institutes of Health. NIH...Turning Discovery Into Health \u00ae. Visit:\u00a0https://t.co/Sq1H7rBx8m\u00a0Privacy Policy:\u00a0https://t.co/0BX8tXlORG",
            "favourites_count": 1570,
            "followers_count": 915020,
            "friends_count": 273,
            "id": 15134240,
            "id_str": "15134240",
            "listed_count": 10235,
            "location": "Bethesda, Maryland, USA",
            "name": "NIH",
            "profile_background_color": "000000",
            "profile_background_image_url": "http://abs.twimg.com/images/themes/theme15/bg.png",
            "profile_background_image_url_https": "https://abs.twimg.com/images/themes/theme15/bg.png",
            "profile_banner_url": "https://pbs.twimg.com/profile_banners/15134240/1557851664",
            "profile_image_url": "http://pbs.twimg.com/profile_images/3443048571/ef5062acfce64a7aef1d75b4934fbee6_normal.png",
            "profile_image_url_https": "https://pbs.twimg.com/profile_images/3443048571/ef5062acfce64a7aef1d75b4934fbee6_normal.png",
            "profile_link_color": "ABB8C2",
            "profile_sidebar_border_color": "000000",
            "profile_sidebar_fill_color": "000000",
            "profile_text_color": "000000",
            "screen_name": "NIH",
            "statuses_count": 12013,
            "url": "https://t.co/lxbTso1Zyy",
            "verified": true
        },
        "user_mentions": []
    },
    "source": "<a href=\"http://twitter.com\" rel=\"nofollow\">Twitter Web Client</a>",
    "text": "RT @NIH: #Idaho received $14.9 million in #NIH-funded research support in FY2018: https://t.co/8nk4PbrH0L #NIHinYourState https://t.co/RQqI\u2026",
    "urls": [
        {
            "expanded_url": "https://bit.ly/2Jz5nFJ",
            "url": "https://t.co/8nk4PbrH0L"
        }
    ],
    "user": {
        "created_at": "Tue Jun 05 22:16:35 +0000 2012",
        "description": "United States Senator for the great state of Idaho.",
        "favourites_count": 744,
        "followers_count": 96401,
        "friends_count": 743,
        "geo_enabled": true,
        "id": 600463589,
        "id_str": "600463589",
        "listed_count": 1742,
        "location": "Idaho & Washington, D.C.",
        "name": "Senator Mike Crapo",
        "profile_background_color": "C0DEED",
        "profile_background_image_url": "http://abs.twimg.com/images/themes/theme1/bg.png",
        "profile_background_image_url_https": "https://abs.twimg.com/images/themes/theme1/bg.png",
        "profile_background_tile": true,
        "profile_banner_url": "https://pbs.twimg.com/profile_banners/600463589/1358530313",
        "profile_image_url": "http://pbs.twimg.com/profile_images/2286763334/atyer80hkqhdwmgk73t0_normal.jpeg",
        "profile_image_url_https": "https://pbs.twimg.com/profile_images/2286763334/atyer80hkqhdwmgk73t0_normal.jpeg",
        "profile_link_color": "0084B4",
        "profile_sidebar_border_color": "FFFFFF",
        "profile_sidebar_fill_color": "DDEEF6",
        "profile_text_color": "333333",
        "profile_use_background_image": true,
        "screen_name": "MikeCrapo",
        "statuses_count": 6558,
        "url": "http://t.co/W6cAM2HKzW",
        "verified": true
    },
    "user_mentions": [
        {
            "id": 15134240,
            "id_str": "15134240",
            "name": "NIH",
            "screen_name": "NIH"
        }
    ]
}