{
    "created_at": "Thu May 02 13:59:21 +0000 2019",
    "hashtags": [],
    "id": 1123950102941523982,
    "id_str": "1123950102941523982",
    "lang": "en",
    "retweet_count": 2,
    "retweeted_status": {
        "created_at": "Thu May 02 13:36:56 +0000 2019",
        "favorite_count": 13,
        "hashtags": [],
        "id": 1123944461732601857,
        "id_str": "1123944461732601857",
        "lang": "en",
        "retweet_count": 2,
        "source": "<a href=\"http://twitter.com\" rel=\"nofollow\">Twitter Web Client</a>",
        "text": "Happening now: Chairman @JimInhofe convenes a hearing on the nomination of General James McConville (@VCSA_PAO) to\u2026 https://t.co/GLv8ESokZq",
        "truncated": true,
        "urls": [
            {
                "expanded_url": "https://twitter.com/i/web/status/1123944461732601857",
                "url": "https://t.co/GLv8ESokZq"
            }
        ],
        "user": {
            "created_at": "Fri Apr 01 15:10:03 +0000 2011",
            "description": "Official source for news from the Republicans on the Senate Armed Services Committee. Chairman @JimInhofe",
            "favourites_count": 246,
            "followers_count": 10641,
            "friends_count": 249,
            "id": 275572403,
            "id_str": "275572403",
            "listed_count": 531,
            "location": "Washington, D.C.",
            "name": "SASC Majority",
            "profile_background_color": "1A1B1F",
            "profile_background_image_url": "http://abs.twimg.com/images/themes/theme9/bg.gif",
            "profile_background_image_url_https": "https://abs.twimg.com/images/themes/theme9/bg.gif",
            "profile_banner_url": "https://pbs.twimg.com/profile_banners/275572403/1360088897",
            "profile_image_url": "http://pbs.twimg.com/profile_images/1299575941/united_states_senate1_normal.jpg",
            "profile_image_url_https": "https://pbs.twimg.com/profile_images/1299575941/united_states_senate1_normal.jpg",
            "profile_link_color": "1D8BC2",
            "profile_sidebar_border_color": "FFFFFF",
            "profile_sidebar_fill_color": "DDEEF6",
            "profile_text_color": "333333",
            "screen_name": "SASCMajority",
            "statuses_count": 1076,
            "url": "https://t.co/trxlM2POEM",
            "verified": true
        },
        "user_mentions": [
            {
                "id": 7270292,
                "id_str": "7270292",
                "name": "Jim Inhofe",
                "screen_name": "JimInhofe"
            }
        ]
    },
    "source": "<a href=\"https://about.twitter.com/products/tweetdeck\" rel=\"nofollow\">TweetDeck</a>",
    "text": "RT @SASCMajority: Happening now: Chairman @JimInhofe convenes a hearing on the nomination of General James McConville (@VCSA_PAO) to be Chi\u2026",
    "urls": [],
    "user": {
        "created_at": "Thu Jul 05 14:39:13 +0000 2007",
        "description": "United States Senator from the great state of Oklahoma.",
        "favourites_count": 93,
        "followers_count": 52355,
        "friends_count": 347,
        "id": 7270292,
        "id_str": "7270292",
        "listed_count": 2164,
        "location": "Oklahoma",
        "name": "Jim Inhofe",
        "profile_background_color": "C0DEED",
        "profile_background_image_url": "http://abs.twimg.com/images/themes/theme1/bg.png",
        "profile_background_image_url_https": "https://abs.twimg.com/images/themes/theme1/bg.png",
        "profile_banner_url": "https://pbs.twimg.com/profile_banners/7270292/1418070273",
        "profile_image_url": "http://pbs.twimg.com/profile_images/847193851496411136/d1spdzhn_normal.jpg",
        "profile_image_url_https": "https://pbs.twimg.com/profile_images/847193851496411136/d1spdzhn_normal.jpg",
        "profile_link_color": "0084B4",
        "profile_sidebar_border_color": "C0DEED",
        "profile_sidebar_fill_color": "DDEEF6",
        "profile_text_color": "333333",
        "screen_name": "JimInhofe",
        "statuses_count": 2008,
        "url": "http://t.co/MsjJPG2F5l",
        "verified": true
    },
    "user_mentions": [
        {
            "id": 275572403,
            "id_str": "275572403",
            "name": "SASC Majority",
            "screen_name": "SASCMajority"
        },
        {
            "id": 7270292,
            "id_str": "7270292",
            "name": "Jim Inhofe",
            "screen_name": "JimInhofe"
        }
    ]
}