{
    "created_at": "Wed May 29 18:29:37 +0000 2019",
    "hashtags": [
        {
            "text": "Blockchain"
        }
    ],
    "id": 1133802591287226368,
    "id_str": "1133802591287226368",
    "lang": "en",
    "retweet_count": 5,
    "retweeted_status": {
        "created_at": "Wed May 29 17:20:12 +0000 2019",
        "favorite_count": 13,
        "hashtags": [
            {
                "text": "Blockchain"
            }
        ],
        "id": 1133785120861806593,
        "id_str": "1133785120861806593",
        "lang": "en",
        "possibly_sensitive": true,
        "retweet_count": 5,
        "source": "<a href=\"https://mobile.twitter.com\" rel=\"nofollow\">Twitter Web App</a>",
        "text": "I applaud @RepTrey Hollingsworth, @RepTedBudd &amp; all members of #Blockchain Caucus in helping make blockchain a U.S.\u2026 https://t.co/BVfTxFv1QV",
        "truncated": true,
        "urls": [
            {
                "expanded_url": "https://twitter.com/i/web/status/1133785120861806593",
                "url": "https://t.co/BVfTxFv1QV"
            }
        ],
        "user": {
            "created_at": "Sun Jul 13 02:41:00 +0000 2014",
            "description": "Director Member Services @DigitalChamber | Bitcoiner Since 2012 | Co-Founded @Cryptolina in 2014 | Formerly @NCCommerce @NCDOT | @EastCarolina @Georgetown Alum",
            "favourites_count": 5348,
            "followers_count": 1247,
            "friends_count": 89,
            "geo_enabled": true,
            "id": 2634274458,
            "id_str": "2634274458",
            "listed_count": 134,
            "location": "Washington, DC",
            "name": "Dan Spuller \ud83d\udc8e",
            "profile_background_color": "C0DEED",
            "profile_background_image_url": "http://abs.twimg.com/images/themes/theme1/bg.png",
            "profile_background_image_url_https": "https://abs.twimg.com/images/themes/theme1/bg.png",
            "profile_banner_url": "https://pbs.twimg.com/profile_banners/2634274458/1563578138",
            "profile_image_url": "http://pbs.twimg.com/profile_images/824674098810941445/D2Xm_BA-_normal.jpg",
            "profile_image_url_https": "https://pbs.twimg.com/profile_images/824674098810941445/D2Xm_BA-_normal.jpg",
            "profile_link_color": "7700B3",
            "profile_sidebar_border_color": "C0DEED",
            "profile_sidebar_fill_color": "DDEEF6",
            "profile_text_color": "333333",
            "profile_use_background_image": true,
            "screen_name": "DanSpuller",
            "statuses_count": 2928
        },
        "user_mentions": [
            {
                "id": 811986281177772032,
                "id_str": "811986281177772032",
                "name": "Trey Hollingsworth",
                "screen_name": "RepTrey"
            },
            {
                "id": 817138492614524928,
                "id_str": "817138492614524928",
                "name": "Ted Budd",
                "screen_name": "RepTedBudd"
            }
        ]
    },
    "source": "<a href=\"http://twitter.com\" rel=\"nofollow\">Twitter Web Client</a>",
    "text": "RT @DanSpuller: I applaud @RepTrey Hollingsworth, @RepTedBudd &amp; all members of #Blockchain Caucus in helping make blockchain a U.S. priorit\u2026",
    "urls": [],
    "user": {
        "created_at": "Thu Jan 05 22:39:33 +0000 2017",
        "default_profile": true,
        "description": "Proudly serving the 13th district of North Carolina. #NC13",
        "favourites_count": 105,
        "followers_count": 11009,
        "friends_count": 270,
        "id": 817138492614524928,
        "id_str": "817138492614524928",
        "listed_count": 345,
        "location": "Davie County, North Carolina",
        "name": "Ted Budd",
        "profile_background_color": "F5F8FA",
        "profile_banner_url": "https://pbs.twimg.com/profile_banners/817138492614524928/1485880195",
        "profile_image_url": "http://pbs.twimg.com/profile_images/987039452483739648/Hs7YypAA_normal.jpg",
        "profile_image_url_https": "https://pbs.twimg.com/profile_images/987039452483739648/Hs7YypAA_normal.jpg",
        "profile_link_color": "1DA1F2",
        "profile_sidebar_border_color": "C0DEED",
        "profile_sidebar_fill_color": "DDEEF6",
        "profile_text_color": "333333",
        "profile_use_background_image": true,
        "screen_name": "RepTedBudd",
        "statuses_count": 1553,
        "url": "https://t.co/VTsvWe0pia",
        "verified": true
    },
    "user_mentions": [
        {
            "id": 2634274458,
            "id_str": "2634274458",
            "name": "Dan Spuller \ud83d\udc8e",
            "screen_name": "DanSpuller"
        },
        {
            "id": 811986281177772032,
            "id_str": "811986281177772032",
            "name": "Trey Hollingsworth",
            "screen_name": "RepTrey"
        },
        {
            "id": 817138492614524928,
            "id_str": "817138492614524928",
            "name": "Ted Budd",
            "screen_name": "RepTedBudd"
        }
    ]
}