{
    "created_at": "Mon Apr 08 21:00:55 +0000 2019",
    "favorite_count": 3,
    "hashtags": [
        {
            "text": "InternationalRomaDay"
        }
    ],
    "id": 1115358884691095571,
    "id_str": "1115358884691095571",
    "lang": "en",
    "retweet_count": 2,
    "source": "<a href=\"http://twitter.com/download/iphone\" rel=\"nofollow\">Twitter for iPhone</a>",
    "text": "Marking #InternationalRomaDay, @RepHastingsFL, along with @SenatorWicker, @Rep_Watkins, &amp; @SenatorCardin, was proud\u2026 https://t.co/Th1iMnlXou",
    "truncated": true,
    "urls": [
        {
            "expanded_url": "https://twitter.com/i/web/status/1115358884691095571",
            "url": "https://t.co/Th1iMnlXou"
        }
    ],
    "user": {
        "created_at": "Tue Apr 08 14:53:21 +0000 2014",
        "default_profile": true,
        "description": "Congressman Alcee L. Hastings represents parts of Broward and Palm Beach counties in the U.S. House of Representatives.",
        "favourites_count": 33,
        "followers_count": 25518,
        "friends_count": 254,
        "geo_enabled": true,
        "id": 2433737761,
        "id_str": "2433737761",
        "listed_count": 662,
        "location": "Florida 20th",
        "name": "Alcee L. Hastings",
        "profile_background_color": "C0DEED",
        "profile_background_image_url": "http://abs.twimg.com/images/themes/theme1/bg.png",
        "profile_background_image_url_https": "https://abs.twimg.com/images/themes/theme1/bg.png",
        "profile_banner_url": "https://pbs.twimg.com/profile_banners/2433737761/1522095008",
        "profile_image_url": "http://pbs.twimg.com/profile_images/978363613609152513/iY5mlH9a_normal.jpg",
        "profile_image_url_https": "https://pbs.twimg.com/profile_images/978363613609152513/iY5mlH9a_normal.jpg",
        "profile_link_color": "1DA1F2",
        "profile_sidebar_border_color": "C0DEED",
        "profile_sidebar_fill_color": "DDEEF6",
        "profile_text_color": "333333",
        "profile_use_background_image": true,
        "screen_name": "RepHastingsFL",
        "statuses_count": 1776,
        "url": "http://t.co/g0E2ojpNr4",
        "verified": true
    },
    "user_mentions": [
        {
            "id": 2433737761,
            "id_str": "2433737761",
            "name": "Alcee L. Hastings",
            "screen_name": "RepHastingsFL"
        },
        {
            "id": 264219447,
            "id_str": "264219447",
            "name": "Senator Roger Wicker",
            "screen_name": "SenatorWicker"
        },
        {
            "id": 1080307235350241280,
            "id_str": "1080307235350241280",
            "name": "Rep. Steve Watkins",
            "screen_name": "Rep_Watkins"
        },
        {
            "id": 109071031,
            "id_str": "109071031",
            "name": "Senator Ben Cardin",
            "screen_name": "SenatorCardin"
        }
    ]
}