{
    "created_at": "Thu Aug 08 14:48:09 +0000 2019",
    "hashtags": [],
    "id": 1159476397754245121,
    "id_str": "1159476397754245121",
    "lang": "en",
    "quoted_status_id": 1158490714914906113,
    "quoted_status_id_str": "1158490714914906113",
    "retweet_count": 10,
    "retweeted_status": {
        "created_at": "Wed Aug 07 20:47:18 +0000 2019",
        "favorite_count": 10,
        "hashtags": [],
        "id": 1159204390403620871,
        "id_str": "1159204390403620871",
        "lang": "en",
        "quoted_status": {
            "created_at": "Mon Aug 05 21:31:24 +0000 2019",
            "favorite_count": 180,
            "hashtags": [],
            "id": 1158490714914906113,
            "id_str": "1158490714914906113",
            "lang": "en",
            "retweet_count": 197,
            "source": "<a href=\"https://about.twitter.com/products/tweetdeck\" rel=\"nofollow\">TweetDeck</a>",
            "text": "CENSUS \ud83e\udd13 ALERT: @uscensusbureau is sending workers to walk through neighborhoods this month through Oct. 18, to mak\u2026 https://t.co/ocSYlqe9c5",
            "truncated": true,
            "urls": [
                {
                    "expanded_url": "https://twitter.com/i/web/status/1158490714914906113",
                    "url": "https://t.co/ocSYlqe9c5"
                }
            ],
            "user": {
                "created_at": "Sat Aug 28 19:28:37 +0000 2010",
                "description": "@NPR national correspondent covering the people, power & money behind the #2020Census | email: hwang@npr.org | signal: 917-397-2639 | \ud83d\udcf8: B. McCabe; LOC",
                "favourites_count": 2068,
                "followers_count": 23019,
                "friends_count": 2906,
                "id": 184128260,
                "id_str": "184128260",
                "listed_count": 452,
                "location": "New York, NY",
                "name": "Hansi Lo Wang",
                "profile_background_color": "000000",
                "profile_background_image_url": "http://abs.twimg.com/images/themes/theme1/bg.png",
                "profile_background_image_url_https": "https://abs.twimg.com/images/themes/theme1/bg.png",
                "profile_banner_url": "https://pbs.twimg.com/profile_banners/184128260/1553822182",
                "profile_image_url": "http://pbs.twimg.com/profile_images/957796956906115073/8uFCZbZd_normal.jpg",
                "profile_image_url_https": "https://pbs.twimg.com/profile_images/957796956906115073/8uFCZbZd_normal.jpg",
                "profile_link_color": "ABB8C2",
                "profile_sidebar_border_color": "000000",
                "profile_sidebar_fill_color": "000000",
                "profile_text_color": "000000",
                "screen_name": "hansilowang",
                "statuses_count": 7092,
                "url": "https://t.co/axPIu7eqts",
                "verified": true
            },
            "user_mentions": [
                {
                    "id": 23092890,
                    "id_str": "23092890",
                    "name": "U.S. Census Bureau",
                    "screen_name": "uscensusbureau"
                }
            ]
        },
        "quoted_status_id": 1158490714914906113,
        "quoted_status_id_str": "1158490714914906113",
        "retweet_count": 10,
        "source": "<a href=\"https://mobile.twitter.com\" rel=\"nofollow\">Twitter Web App</a>",
        "text": "the @uscensusbureau is sending workers to walk neighborhoods. Check out these tips to learn how to identify a US Ce\u2026 https://t.co/6EVqZPU4FW",
        "truncated": true,
        "urls": [
            {
                "expanded_url": "https://twitter.com/i/web/status/1159204390403620871",
                "url": "https://t.co/6EVqZPU4FW"
            }
        ],
        "user": {
            "created_at": "Fri Aug 28 18:00:50 +0000 2009",
            "description": "Official account for County of Sacramento. Get more news at http://t.co/CEX41JlGor or  https://t.co/sD3FxvTTEp",
            "favourites_count": 5758,
            "followers_count": 15165,
            "friends_count": 1203,
            "id": 69651972,
            "id_str": "69651972",
            "listed_count": 240,
            "location": "Sacramento County, CA",
            "name": "Sacramento County",
            "profile_background_color": "2270B5",
            "profile_background_image_url": "http://abs.twimg.com/images/themes/theme1/bg.png",
            "profile_background_image_url_https": "https://abs.twimg.com/images/themes/theme1/bg.png",
            "profile_banner_url": "https://pbs.twimg.com/profile_banners/69651972/1528393970",
            "profile_image_url": "http://pbs.twimg.com/profile_images/378800000182962190/074e1ffc013acce8fae5c19b201ebde3_normal.png",
            "profile_image_url_https": "https://pbs.twimg.com/profile_images/378800000182962190/074e1ffc013acce8fae5c19b201ebde3_normal.png",
            "profile_link_color": "F76605",
            "profile_sidebar_border_color": "BDDCAD",
            "profile_sidebar_fill_color": "C6D8F7",
            "profile_text_color": "333333",
            "profile_use_background_image": true,
            "screen_name": "SacCountyCA",
            "statuses_count": 5517,
            "url": "http://t.co/P53m5SFGDw",
            "verified": true
        },
        "user_mentions": [
            {
                "id": 23092890,
                "id_str": "23092890",
                "name": "U.S. Census Bureau",
                "screen_name": "uscensusbureau"
            }
        ]
    },
    "source": "<a href=\"https://mobile.twitter.com\" rel=\"nofollow\">Twitter Web App</a>",
    "text": "RT @SacCountyCA: the @uscensusbureau is sending workers to walk neighborhoods. Check out these tips to learn how to identify a US Census wo\u2026",
    "urls": [],
    "user": {
        "created_at": "Fri Nov 16 01:39:54 +0000 2012",
        "default_profile": true,
        "description": "Father, husband, doctor. Proudly representing Sacramento County, California in the U.S. House of Representatives #CA07.",
        "favourites_count": 200,
        "followers_count": 34109,
        "friends_count": 746,
        "geo_enabled": true,
        "id": 950783972,
        "id_str": "950783972",
        "listed_count": 951,
        "location": "Elk Grove, California",
        "name": "Ami Bera, M.D.",
        "profile_background_color": "C0DEED",
        "profile_background_image_url": "http://abs.twimg.com/images/themes/theme1/bg.png",
        "profile_background_image_url_https": "https://abs.twimg.com/images/themes/theme1/bg.png",
        "profile_banner_url": "https://pbs.twimg.com/profile_banners/950783972/1562685257",
        "profile_image_url": "http://pbs.twimg.com/profile_images/722533785481248769/LJz8Qkxj_normal.jpg",
        "profile_image_url_https": "https://pbs.twimg.com/profile_images/722533785481248769/LJz8Qkxj_normal.jpg",
        "profile_link_color": "1DA1F2",
        "profile_sidebar_border_color": "C0DEED",
        "profile_sidebar_fill_color": "DDEEF6",
        "profile_text_color": "333333",
        "profile_use_background_image": true,
        "screen_name": "RepBera",
        "statuses_count": 3848,
        "url": "https://t.co/sQPbW1JPOd",
        "verified": true
    },
    "user_mentions": [
        {
            "id": 69651972,
            "id_str": "69651972",
            "name": "Sacramento County",
            "screen_name": "SacCountyCA"
        },
        {
            "id": 23092890,
            "id_str": "23092890",
            "name": "U.S. Census Bureau",
            "screen_name": "uscensusbureau"
        }
    ]
}